[
  {
    "session_id": "2025-09-16_08-17-54",
    "drama_name": "天降小饕餮，我收你们来啦",
    "output_dir": "/Volumes/爆爆盘/短剧剪辑/9.16导出/天降小饕餮，我收你们来啦",
    "materials_count": 18,
    "completed": true,
    "size_mb": 9238.026133537292
  },
  {
    "session_id": "2025-09-16_10-28-51",
    "drama_name": "刚重生就把未来老婆吓晕了",
    "output_dir": "/Volumes/爆爆盘/短剧剪辑/9.17导出/刚重生就把未来老婆吓晕了",
    "materials_count": 18,
    "completed": true,
    "size_mb": 7523.5273723602295
  },
  {
    "session_id": "2025-09-16_16-12-50",
    "drama_name": "万军跪迎：长公主回朝登基",
    "output_dir": "/Volumes/爆爆盘/短剧剪辑/9.17导出/万军跪迎：长公主回朝登基-001",
    "materials_count": 18,
    "completed": true,
    "size_mb": 9451.120826721191
  },
  {
    "session_id": "2025-09-16_16-12-50",
    "drama_name": "从今天开始做男神",
    "output_dir": "/Volumes/爆爆盘/短剧剪辑/9.17导出/从今天开始做男神",
    "materials_count": 18,
    "completed": true,
    "size_mb": 9139.838500976562
  },
  {
    "session_id": "2025-09-16_16-12-50",
    "drama_name": "冷眼旁观的她",
    "output_dir": "/Volumes/爆爆盘/短剧剪辑/9.17导出/冷眼旁观的她",
    "materials_count": 18,
    "completed": true,
    "size_mb": 9130.145034790039
  },
  {
    "session_id": "2025-09-16_16-12-50",
    "drama_name": "别惹真千金，她爸是超级女儿奴",
    "output_dir": "/Volumes/爆爆盘/短剧剪辑/9.17导出/别惹真千金，她爸是超级女儿奴",
    "materials_count": 18,
    "completed": true,
    "size_mb": 9358.075646400452
  },
  {
    "session_id": "2025-09-16_16-12-50",
    "drama_name": "前夫哥，你有点糟糕",
    "output_dir": "/Volumes/爆爆盘/短剧剪辑/9.17导出/前夫哥，你有点糟糕",
    "materials_count": 18,
    "completed": true,
    "size_mb": 8626.022595405579
  },
  {
    "session_id": "2025-09-16_16-12-50",
    "drama_name": "国公府弃女，被狼群宠成小公主",
    "output_dir": "/Volumes/爆爆盘/短剧剪辑/9.17导出/国公府弃女，被狼群宠成小公主",
    "materials_count": 18,
    "completed": true,
    "size_mb": 9225.835453033447
  },
  {
    "session_id": "2025-09-16_16-12-50",
    "drama_name": "天降甜妻太嚣张",
    "output_dir": "/Volumes/爆爆盘/短剧剪辑/9.17导出/天降甜妻太嚣张",
    "materials_count": 18,
    "completed": true,
    "size_mb": 9630.335196495056
  },
  {
    "session_id": "2025-09-16_16-12-50",
    "drama_name": "家有旺夫小福妻",
    "output_dir": "/Volumes/爆爆盘/短剧剪辑/9.17导出/家有旺夫小福妻",
    "materials_count": 18,
    "completed": true,
    "size_mb": 9318.237010002136
  },
  {
    "session_id": "2025-09-16_16-12-50",
    "drama_name": "废太子的白月光是仙女",
    "output_dir": "/Volumes/爆爆盘/短剧剪辑/9.17导出/废太子的白月光是仙女",
    "materials_count": 18,
    "completed": true,
    "size_mb": 9296.341248512268
  },
  {
    "session_id": "2025-09-16_16-12-50",
    "drama_name": "穿越80后，捡来的老公超给力",
    "output_dir": "/Volumes/爆爆盘/短剧剪辑/9.17导出/穿越80后，捡来的老公超给力",
    "materials_count": 18,
    "completed": true,
    "size_mb": 9509.392887115479
  },
  {
    "session_id": "2025-09-16_16-12-50",
    "drama_name": "老屋檐下",
    "output_dir": "/Volumes/爆爆盘/短剧剪辑/9.17导出/老屋檐下",
    "materials_count": 18,
    "completed": true,
    "size_mb": 9235.116436004639
  },
  {
    "session_id": "2025-09-16_16-12-50",
    "drama_name": "胭脂扣君心",
    "output_dir": "/Volumes/爆爆盘/短剧剪辑/9.17导出/胭脂扣君心",
    "materials_count": 12,
    "completed": false,
    "size_mb": 6348.9177169799805
  },
  {
    "session_id": "2025-09-16_16-12-50",
    "drama_name": "萌宝福星四岁半",
    "output_dir": "/Volumes/爆爆盘/短剧剪辑/9.17导出/萌宝福星四岁半",
    "materials_count": 18,
    "completed": true,
    "size_mb": 9049.010599136353
  },
  {
    "session_id": "2025-09-16_16-12-50",
    "drama_name": "诱玫瑰心动",
    "output_dir": "/Volumes/爆爆盘/短剧剪辑/9.17导出/诱玫瑰心动",
    "materials_count": 18,
    "completed": true,
    "size_mb": 9286.620945930481
  },
  {
    "session_id": "2025-09-16_16-12-50",
    "drama_name": "重生之超级投资天才",
    "output_dir": "/Volumes/爆爆盘/短剧剪辑/9.17导出/重生之超级投资天才",
    "materials_count": 18,
    "completed": false,
    "size_mb": 9131.319081306458
  },
  {
    "session_id": "2025-09-16_16-12-50",
    "drama_name": "重生后我带女婿发家致富",
    "output_dir": "/Volumes/爆爆盘/短剧剪辑/9.17导出/重生后我带女婿发家致富",
    "materials_count": 18,
    "completed": true,
    "size_mb": 9484.350445747375
  }
]