[
  {
    "session_id": "2025-09-18_10-10-25",
    "date": "2025-09-18",
    "output_dir": "/Volumes/爆爆盘/短剧剪辑/9.18导出/侯门悍妻：夫人凶名在外，本官得宠着",
    "materials": [
      "9.18-侯门悍妻：夫人凶名在外，本官得宠着-xh-01.mp4",
      "9.18-侯门悍妻：夫人凶名在外，本官得宠着-xh-02.mp4",
      "9.18-侯门悍妻：夫人凶名在外，本官得宠着-xh-03.mp4",
      "9.18-侯门悍妻：夫人凶名在外，本官得宠着-xh-04.mp4",
      "9.18-侯门悍妻：夫人凶名在外，本官得宠着-xh-05.mp4",
      "9.18-侯门悍妻：夫人凶名在外，本官得宠着-xh-06.mp4",
      "9.18-侯门悍妻：夫人凶名在外，本官得宠着-xh-07.mp4",
      "9.18-侯门悍妻：夫人凶名在外，本官得宠着-xh-08.mp4",
      "9.18-侯门悍妻：夫人凶名在外，本官得宠着-xh-09.mp4",
      "9.18-侯门悍妻：夫人凶名在外，本官得宠着-xh-10.mp4",
      "9.18-侯门悍妻：夫人凶名在外，本官得宠着-xh-11.mp4",
      "9.18-侯门悍妻：夫人凶名在外，本官得宠着-xh-12.mp4",
      "9.18-侯门悍妻：夫人凶名在外，本官得宠着-xh-13.mp4",
      "9.18-侯门悍妻：夫人凶名在外，本官得宠着-xh-14.mp4",
      "9.18-侯门悍妻：夫人凶名在外，本官得宠着-xh-15.mp4",
      "9.18-侯门悍妻：夫人凶名在外，本官得宠着-xh-16.mp4",
      "9.18-侯门悍妻：夫人凶名在外，本官得宠着-xh-17.mp4",
      "9.18-侯门悍妻：夫人凶名在外，本官得宠着-xh-18.mp4"
    ],
    "materials_count": 18,
    "completed": true,
    "size_mb": 9637.664669036865,
    "processing_time": 3515.1269290447235
  }
]