[
  {
    "session_id": "2025-09-30_01-17-17",
    "date": "2025-09-30",
    "output_dir": "/Volumes/爆爆盘/短剧剪辑/10.1/八岁萌娃，单枪匹马挑皇城",
    "materials": [
      "10.1-八岁萌娃，单枪匹马挑皇城-xh-02.mp4",
      "10.1-八岁萌娃，单枪匹马挑皇城-xh-03.mp4",
      "10.1-八岁萌娃，单枪匹马挑皇城-xh-05.mp4",
      "10.1-八岁萌娃，单枪匹马挑皇城-xh-06.mp4",
      "10.1-八岁萌娃，单枪匹马挑皇城-xh-01.mp4",
      "10.1-八岁萌娃，单枪匹马挑皇城-xh-04.mp4",
      "10.1-八岁萌娃，单枪匹马挑皇城-xh-09.mp4",
      "10.1-八岁萌娃，单枪匹马挑皇城-xh-07.mp4",
      "10.1-八岁萌娃，单枪匹马挑皇城-xh-08.mp4",
      "10.1-八岁萌娃，单枪匹马挑皇城-xh-11.mp4",
      "10.1-八岁萌娃，单枪匹马挑皇城-xh-12.mp4",
      "10.1-八岁萌娃，单枪匹马挑皇城-xh-10.mp4",
      "10.1-八岁萌娃，单枪匹马挑皇城-xh-13.mp4",
      "10.1-八岁萌娃，单枪匹马挑皇城-xh-15.mp4",
      "10.1-八岁萌娃，单枪匹马挑皇城-xh-14.mp4"
    ],
    "materials_count": 15,
    "completed": true,
    "size_mb": 7831.9357080459595,
    "processing_time": 1365.3480830192566
  },
  {
    "session_id": "2025-09-30_17-17-20",
    "date": "2025-09-30",
    "output_dir": "/Volumes/爆爆盘/短剧剪辑/10.10/八岁萌娃，单枪匹马挑皇城",
    "materials": [
      "10.10-八岁萌娃，单枪匹马挑皇城-xh-01.mp4"
    ],
    "materials_count": 1,
    "completed": true,
    "size_mb": 56.287309646606445,
    "processing_time": 39.06174898147583
  }
]