[
  {
    "session_id": "2025-09-16_16-12-50",
    "date": "2025-09-16",
    "output_dir": "/Volumes/爆爆盘/短剧剪辑/9.17导出/前夫哥，你有点糟糕",
    "materials": [
      "9.17-前夫哥，你有点糟糕-xh-01.mp4",
      "9.17-前夫哥，你有点糟糕-xh-02.mp4",
      "9.17-前夫哥，你有点糟糕-xh-03.mp4",
      "9.17-前夫哥，你有点糟糕-xh-04.mp4",
      "9.17-前夫哥，你有点糟糕-xh-05.mp4",
      "9.17-前夫哥，你有点糟糕-xh-06.mp4",
      "9.17-前夫哥，你有点糟糕-xh-07.mp4",
      "9.17-前夫哥，你有点糟糕-xh-08.mp4",
      "9.17-前夫哥，你有点糟糕-xh-09.mp4",
      "9.17-前夫哥，你有点糟糕-xh-10.mp4",
      "9.17-前夫哥，你有点糟糕-xh-11.mp4",
      "9.17-前夫哥，你有点糟糕-xh-12.mp4",
      "9.17-前夫哥，你有点糟糕-xh-13.mp4",
      "9.17-前夫哥，你有点糟糕-xh-14.mp4",
      "9.17-前夫哥，你有点糟糕-xh-15.mp4",
      "9.17-前夫哥，你有点糟糕-xh-16.mp4",
      "9.17-前夫哥，你有点糟糕-xh-17.mp4",
      "9.17-前夫哥，你有点糟糕-xh-18.mp4"
    ],
    "materials_count": 18,
    "completed": true,
    "size_mb": 8626.022595405579,
    "processing_time": 1817.8667998313904
  },
  {
    "session_id": "2025-09-22_16-40-37",
    "date": "2025-09-22",
    "output_dir": "/Volumes/爆爆盘/短剧剪辑/9.22导出/前夫哥，你有点糟糕",
    "materials": [
      "9.22-前夫哥，你有点糟糕-xh-01.mp4",
      "9.22-前夫哥，你有点糟糕-xh-02.mp4",
      "9.22-前夫哥，你有点糟糕-xh-03.mp4",
      "9.22-前夫哥，你有点糟糕-xh-04.mp4",
      "9.22-前夫哥，你有点糟糕-xh-05.mp4",
      "9.22-前夫哥，你有点糟糕-xh-06.mp4",
      "9.22-前夫哥，你有点糟糕-xh-07.mp4",
      "9.22-前夫哥，你有点糟糕-xh-08.mp4",
      "9.22-前夫哥，你有点糟糕-xh-09.mp4",
      "9.22-前夫哥，你有点糟糕-xh-10.mp4",
      "9.22-前夫哥，你有点糟糕-xh-11.mp4",
      "9.22-前夫哥，你有点糟糕-xh-12.mp4",
      "9.22-前夫哥，你有点糟糕-xh-13.mp4",
      "9.22-前夫哥，你有点糟糕-xh-14.mp4",
      "9.22-前夫哥，你有点糟糕-xh-15.mp4"
    ],
    "materials_count": 15,
    "completed": true,
    "size_mb": 7209.2252769470215,
    "processing_time": 1414.0576016902924
  }
]