[
  {
    "session_id": "2025-09-19_16-00-48",
    "date": "2025-09-19",
    "output_dir": "/Volumes/爆爆盘/短剧剪辑/9.20导出/雾锁青松终见月",
    "materials": [
      "9.20-雾锁青松终见月-xh-01.mp4",
      "9.20-雾锁青松终见月-xh-02.mp4",
      "9.20-雾锁青松终见月-xh-03.mp4",
      "9.20-雾锁青松终见月-xh-04.mp4",
      "9.20-雾锁青松终见月-xh-05.mp4",
      "9.20-雾锁青松终见月-xh-06.mp4",
      "9.20-雾锁青松终见月-xh-07.mp4",
      "9.20-雾锁青松终见月-xh-08.mp4",
      "9.20-雾锁青松终见月-xh-09.mp4",
      "9.20-雾锁青松终见月-xh-10.mp4",
      "9.20-雾锁青松终见月-xh-11.mp4",
      "9.20-雾锁青松终见月-xh-12.mp4",
      "9.20-雾锁青松终见月-xh-13.mp4",
      "9.20-雾锁青松终见月-xh-14.mp4",
      "9.20-雾锁青松终见月-xh-15.mp4"
    ],
    "materials_count": 15,
    "completed": true,
    "size_mb": 7711.760233879089,
    "processing_time": 1576.5640277862549
  },
  {
    "session_id": "2025-09-21_00-41-42",
    "date": "2025-09-21",
    "output_dir": "/Volumes/爆爆盘/短剧剪辑/9.22导出/雾锁青松终见月",
    "materials": [
      "9.22-雾锁青松终见月-xh-01.mp4",
      "9.22-雾锁青松终见月-xh-02.mp4",
      "9.22-雾锁青松终见月-xh-03.mp4",
      "9.22-雾锁青松终见月-xh-04.mp4",
      "9.22-雾锁青松终见月-xh-05.mp4",
      "9.22-雾锁青松终见月-xh-06.mp4",
      "9.22-雾锁青松终见月-xh-07.mp4",
      "9.22-雾锁青松终见月-xh-08.mp4",
      "9.22-雾锁青松终见月-xh-09.mp4",
      "9.22-雾锁青松终见月-xh-10.mp4",
      "9.22-雾锁青松终见月-xh-11.mp4",
      "9.22-雾锁青松终见月-xh-12.mp4",
      "9.22-雾锁青松终见月-xh-13.mp4",
      "9.22-雾锁青松终见月-xh-14.mp4",
      "9.22-雾锁青松终见月-xh-15.mp4"
    ],
    "materials_count": 15,
    "completed": true,
    "size_mb": 7779.940300941467,
    "processing_time": 1459.1622648239136
  },
  {
    "session_id": "2025-09-21_16-20-06",
    "date": "2025-09-21",
    "output_dir": "/Volumes/爆爆盘/短剧剪辑/9.23导出/雾锁青松终见月",
    "materials": [
      "9.23-雾锁青松终见月-xh-01.mp4",
      "9.23-雾锁青松终见月-xh-02.mp4",
      "9.23-雾锁青松终见月-xh-03.mp4",
      "9.23-雾锁青松终见月-xh-04.mp4",
      "9.23-雾锁青松终见月-xh-05.mp4",
      "9.23-雾锁青松终见月-xh-06.mp4",
      "9.23-雾锁青松终见月-xh-07.mp4",
      "9.23-雾锁青松终见月-xh-08.mp4",
      "9.23-雾锁青松终见月-xh-09.mp4",
      "9.23-雾锁青松终见月-xh-10.mp4",
      "9.23-雾锁青松终见月-xh-11.mp4",
      "9.23-雾锁青松终见月-xh-12.mp4",
      "9.23-雾锁青松终见月-xh-13.mp4",
      "9.23-雾锁青松终见月-xh-14.mp4",
      "9.23-雾锁青松终见月-xh-15.mp4"
    ],
    "materials_count": 15,
    "completed": true,
    "size_mb": 7897.248952865601,
    "processing_time": 1595.0245969295502
  },
  {
    "session_id": "2025-09-30_15-20-27",
    "date": "2025-09-30",
    "output_dir": "/Volumes/爆爆盘/短剧剪辑/10.3/雾锁青松终见月",
    "materials": [
      "10.3-雾锁青松终见月-xh-04.mp4",
      "10.3-雾锁青松终见月-xh-05.mp4",
      "10.3-雾锁青松终见月-xh-02.mp4",
      "10.3-雾锁青松终见月-xh-06.mp4",
      "10.3-雾锁青松终见月-xh-03.mp4",
      "10.3-雾锁青松终见月-xh-01.mp4",
      "10.3-雾锁青松终见月-xh-07.mp4",
      "10.3-雾锁青松终见月-xh-12.mp4",
      "10.3-雾锁青松终见月-xh-09.mp4",
      "10.3-雾锁青松终见月-xh-10.mp4",
      "10.3-雾锁青松终见月-xh-08.mp4",
      "10.3-雾锁青松终见月-xh-11.mp4",
      "10.3-雾锁青松终见月-xh-13.mp4",
      "10.3-雾锁青松终见月-xh-14.mp4",
      "10.3-雾锁青松终见月-xh-15.mp4"
    ],
    "materials_count": 15,
    "completed": true,
    "size_mb": 7899.724012374878,
    "processing_time": 1344.0235810279846
  },
  {
    "session_id": "2025-10-03_10-40-48",
    "date": "2025-10-03",
    "output_dir": "/Volumes/爆爆盘/短剧剪辑/10.5导出/雾锁青松终见月",
    "materials": [
      "10.5-雾锁青松终见月-xh-01.mp4",
      "10.5-雾锁青松终见月-xh-02.mp4",
      "10.5-雾锁青松终见月-xh-03.mp4",
      "10.5-雾锁青松终见月-xh-04.mp4",
      "10.5-雾锁青松终见月-xh-05.mp4",
      "10.5-雾锁青松终见月-xh-06.mp4",
      "10.5-雾锁青松终见月-xh-07.mp4",
      "10.5-雾锁青松终见月-xh-08.mp4",
      "10.5-雾锁青松终见月-xh-09.mp4",
      "10.5-雾锁青松终见月-xh-10.mp4",
      "10.5-雾锁青松终见月-xh-11.mp4",
      "10.5-雾锁青松终见月-xh-12.mp4",
      "10.5-雾锁青松终见月-xh-13.mp4",
      "10.5-雾锁青松终见月-xh-14.mp4",
      "10.5-雾锁青松终见月-xh-15.mp4"
    ],
    "materials_count": 15,
    "completed": true,
    "size_mb": 7799.83270072937,
    "processing_time": 1717.4530868530273
  },
  {
    "session_id": "2025-10-06_08-16-17",
    "date": "2025-10-06",
    "output_dir": "/Volumes/爆爆盘/短剧剪辑/10.6导出/雾锁青松终见月",
    "materials": [
      "10.6-雾锁青松终见月-xh-01.mp4",
      "10.6-雾锁青松终见月-xh-02.mp4",
      "10.6-雾锁青松终见月-xh-03.mp4",
      "10.6-雾锁青松终见月-xh-04.mp4",
      "10.6-雾锁青松终见月-xh-05.mp4",
      "10.6-雾锁青松终见月-xh-06.mp4",
      "10.6-雾锁青松终见月-xh-07.mp4",
      "10.6-雾锁青松终见月-xh-08.mp4",
      "10.6-雾锁青松终见月-xh-09.mp4",
      "10.6-雾锁青松终见月-xh-10.mp4",
      "10.6-雾锁青松终见月-xh-11.mp4",
      "10.6-雾锁青松终见月-xh-12.mp4",
      "10.6-雾锁青松终见月-xh-13.mp4",
      "10.6-雾锁青松终见月-xh-14.mp4",
      "10.6-雾锁青松终见月-xh-15.mp4"
    ],
    "materials_count": 15,
    "completed": true,
    "size_mb": 7876.232464790344,
    "processing_time": 1465.4171199798584
  },
  {
    "session_id": "2025-10-11_00-14-27",
    "date": "2025-10-11",
    "output_dir": "/Volumes/爆爆盘/短剧剪辑/10.11导出/雾锁青松终见月",
    "materials": [
      "10.11-雾锁青松终见月-xh-01.mp4",
      "10.11-雾锁青松终见月-xh-02.mp4",
      "10.11-雾锁青松终见月-xh-03.mp4",
      "10.11-雾锁青松终见月-xh-04.mp4",
      "10.11-雾锁青松终见月-xh-05.mp4",
      "10.11-雾锁青松终见月-xh-06.mp4",
      "10.11-雾锁青松终见月-xh-07.mp4",
      "10.11-雾锁青松终见月-xh-08.mp4",
      "10.11-雾锁青松终见月-xh-09.mp4",
      "10.11-雾锁青松终见月-xh-10.mp4",
      "10.11-雾锁青松终见月-xh-11.mp4",
      "10.11-雾锁青松终见月-xh-12.mp4",
      "10.11-雾锁青松终见月-xh-13.mp4",
      "10.11-雾锁青松终见月-xh-14.mp4",
      "10.11-雾锁青松终见月-xh-15.mp4"
    ],
    "materials_count": 15,
    "completed": true,
    "size_mb": 7913.994404792786,
    "processing_time": 1434.4988808631897
  }
]