{
  "date": "2025-09-15",
  "sessions": [
    "2025-09-15_13-26-55",
    "2025-09-15_19-47-44",
    "2025-09-15_23-27-21"
  ],
  "total_dramas": 29,
  "successful_dramas": 27,
  "total_materials": 522,
  "total_size_mb": 241883.72410202026,
  "total_processing_time": 50838.5127184391,
  "unique_dramas": [
    "专业和亲，副业谐星",
    "原来我也是白月光",
    "姐姐结婚，我也结",
    "秘色棋局",
    "萌宝重生助妈咪逆风翻盘",
    "郡主来破案，神奇动物在哪里",
    "重生校花追不停！我靠系统逆袭",
    "重生灾荒年，我靠种田发家护嫂",
    "风起时不说爱你",
    "云散见星光",
    "七零，踹白月光后下乡发家娶村花",
    "云家的小棉袄奶甜奶软",
    "傅爷的小青梅又飒又美",
    "八零：天降福宝竟是天道亲闺女",
    "前妻不哭，我有助女为乐系统",
    "回到民国成僵尸，我的儿子是道长",
    "娶妻就变强：且看我横扫北蛮",
    "嫡母归来，国公府上下听令",
    "当爱以星光为牢",
    "我成了后悔文男主",
    "江湖：千门八将",
    "真千金她是学霸",
    "福星奶团来旺家，帅府全家宠不停",
    "被父皇猜忌后我选择统领天下",
    "重生后，女神的她竟抢着要给我生大儿",
    "重生后，嫡兄们都后悔了",
    "长姐归来！尔等皆是臣",
    "难得夫妻是少年"
  ]
}